easy_chromedriver_windows_install
