Metadata-Version: 2.1
Name: easy-chromedriver-windows-install
Version: 0.0.2
Summary: Download chromedriver easily on Windows
Author: Luan Grabher
Author-email: luanggcontato@gmail.com
License: MIT License
Keywords: chromedriver selenium webdriver
License-File: LICENSE
